uart_rx.v
// ==============================================================================
// Module: uart_rx
// Description: UART Receiver (RX) module with 16x oversampling.
//              Detects falling edge of start bit, verifies start bit stability
//              at center of bit (tick 7), samples 8 data bits at center (tick 15),
//              and checks stop bit for frame errors.
// ==============================================================================

`timescale 1ns / 1ps

module uart_rx (
    input  wire       clk,
    input  wire       rst_n,
    input  wire       rx,            // Serial input line
    input  wire       tick_16x,      // 16x oversampling baud tick
    output reg  [7:0] rx_data,       // Received byte
    output reg        rx_valid,      // 1-cycle pulse when data byte is valid
    output reg        frame_error    // High if stop bit was not sampled high
);

    // FSM State Encoding
    localparam [2:0]
        STATE_IDLE  = 3'b000,
        STATE_START = 3'b001,
        STATE_DATA  = 3'b010,
        STATE_STOP  = 3'b011,
        STATE_DONE  = 3'b100;

    reg [2:0] state;
    reg [3:0] sample_cnt;  // 0 to 15 counter for 16x oversampling
    reg [2:0] bit_index;
    reg [7:0] shift_reg;
    reg       rx_sync1, rx_sync2; // 2-stage input synchronizer to prevent metastability

    // Synchronize asynchronous RX line to system clock
    always @(posedge clk or negedge rst_n) begin
        if (!rst_n) begin
            rx_sync1 <= 1'b1;
            rx_sync2 <= 1'b1;
        end else begin
            rx_sync1 <= rx;
            rx_sync2 <= rx_sync1;
        end
    end

    // Receiver FSM
    always @(posedge clk or negedge rst_n) begin
        if (!rst_n) begin
            state       <= STATE_IDLE;
            sample_cnt  <= 4'd0;
            bit_index   <= 3'd0;
            shift_reg   <= 8'd0;
            rx_data     <= 8'd0;
            rx_valid    <= 1'b0;
            frame_error <= 1'b0;
        end else begin
            rx_valid    <= 1'b0; // Default pulse low
            frame_error <= 1'b0;

            case (state)
                STATE_IDLE: begin
                    sample_cnt <= 4'd0;
                    bit_index  <= 3'd0;
                    // Detect falling edge of start bit
                    if (!rx_sync2) begin
                        state <= STATE_START;
                    end
                end

                STATE_START: begin
                    if (tick_16x) begin
                        if (sample_cnt == 4'd7) begin
                            // Sample at middle of start bit (tick 7)
                            if (!rx_sync2) begin
                                sample_cnt <= 4'd0; // Valid start bit confirmed
                                state      <= STATE_DATA;
                            end else begin
                                state      <= STATE_IDLE; // False alarm/glitch
                            end
                        end else begin
                            sample_cnt <= sample_cnt + 1'b1;
                        end
                    end
                end

                STATE_DATA: begin
                    if (tick_16x) begin
                        if (sample_cnt == 4'd15) begin
                            sample_cnt            <= 4'd0;
                            shift_reg[bit_index]  <= rx_sync2; // Sample data bit at center
                            if (bit_index == 3'd7) begin
                                state <= STATE_STOP;
                            end else begin
                                bit_index <= bit_index + 1'b1;
                            end
                        end else begin
                            sample_cnt <= sample_cnt + 1'b1;
                        end
                    end
                end

                STATE_STOP: begin
                    if (tick_16x) begin
                        if (sample_cnt == 4'd15) begin
                            sample_cnt <= 4'd0;
                            if (rx_sync2) begin // Stop bit should be HIGH
                                rx_data  <= shift_reg;
                                rx_valid <= 1'b1;
                            end else begin
                                frame_error <= 1'b1;
                            end
                            state <= STATE_IDLE;
                        end else begin
                            sample_cnt <= sample_cnt + 1'b1;
                        end
                    end
                end

                default: state <= STATE_IDLE;
            endcase
        end
    end

endmodule

uart_tx.v
// ==============================================================================
// Module: uart_tx
// Description: UART Transmitter (TX) module.
//              Serializes 8-bit parallel data into UART frame format:
//              1 Start Bit (0) -> 8 Data Bits (LSB first) -> 1 Stop Bit (1).
// ==============================================================================

`timescale 1ns / 1ps

module uart_tx (
    input  wire       clk,
    input  wire       rst_n,
    input  wire       tx_start,      // Trigger transmission
    input  wire       baud_tick,     // 1x Baud rate tick
    input  wire [7:0] tx_data,       // Data byte to transmit
    output reg        tx,            // Serial output line
    output reg        tx_busy,       // High while transmission in progress
    output reg        tx_done        // 1-cycle pulse upon completion
);

    // FSM State Encoding
    localparam [2:0]
        STATE_IDLE  = 3'b000,
        STATE_START = 3'b001,
        STATE_DATA  = 3'b010,
        STATE_STOP  = 3'b011,
        STATE_DONE  = 3'b100;

    reg [2:0] state;
    reg [2:0] bit_index;
    reg [7:0] data_reg;

    always @(posedge clk or negedge rst_n) begin
        if (!rst_n) begin
            state     <= STATE_IDLE;
            tx        <= 1'b1; // Idle line is HIGH in UART
            tx_busy   <= 1'b0;
            tx_done   <= 1'b0;
            bit_index <= 3'd0;
            data_reg  <= 8'd0;
        end else begin
            tx_done <= 1'b0; // Default pulse low

            case (state)
                STATE_IDLE: begin
                    tx      <= 1'b1;
                    tx_busy <= 1'b0;
                    if (tx_start) begin
                        data_reg  <= tx_data;
                        tx_busy   <= 1'b1;
                        state     <= STATE_START;
                    end
                end

                STATE_START: begin
                    tx <= 1'b0; // Drive Start Bit (LOW)
                    if (baud_tick) begin
                        bit_index <= 3'd0;
                        state     <= STATE_DATA;
                    end
                end

                STATE_DATA: begin
                    tx <= data_reg[bit_index]; // Transmit LSB first
                    if (baud_tick) begin
                        if (bit_index == 3'd7) begin
                            state <= STATE_STOP;
                        end else begin
                            bit_index <= bit_index + 1'b1;
                        end
                    end
                end

                STATE_STOP: begin
                    tx <= 1'b1; // Drive Stop Bit (HIGH)
                    if (baud_tick) begin
                        state <= STATE_DONE;
                    end
                end

                STATE_DONE: begin
                    tx_done <= 1'b1;
                    tx_busy <= 1'b0;
                    state   <= STATE_IDLE;
                end

                default: state <= STATE_IDLE;
            endcase
        end
    end

endmodule

baud_gen.v
// ==============================================================================
// Module: baud_gen
// Description: Parameterized Baud Rate Generator.
//              Generates a 16x oversampling tick for the UART Receiver (RX)
//              and a 1x baud tick for the UART Transmitter (TX).
//
// Calculation:
//   ACC_LIMIT_16X = CLK_FREQ / (BAUD_RATE * 16)
//   Example: 50 MHz clock, 115200 baud:
//   50,000,000 / (115200 * 16) = 27.12 -> 27 cycles
// ==============================================================================

`timescale 1ns / 1ps

module baud_gen #(
    parameter CLK_FREQ  = 50000000, // 50 MHz
    parameter BAUD_RATE = 115200
)(
    input  wire clk,
    input  wire rst_n,
    output reg  tick_16x,           // 16x oversampling tick for RX
    output reg  tick_1x             // 1x baud tick for TX
);

    localparam LIMIT_16X = CLK_FREQ / (BAUD_RATE * 16);
    localparam COUNT_WIDTH = 16;

    reg [COUNT_WIDTH-1:0] count_16x;
    reg [3:0]             count_1x;

    // 16x Baud Tick Generator
    always @(posedge clk or negedge rst_n) begin
        if (!rst_n) begin
            count_16x <= 0;
            tick_16x  <= 0;
        end else if (count_16x == LIMIT_16X - 1) begin
            count_16x <= 0;
            tick_16x  <= 1'b1;
        end else begin
            count_16x <= count_16x + 1'b1;
            tick_16x  <= 1'b0;
        end
    end

    // 1x Baud Tick Generator (divide 16x tick by 16)
    always @(posedge clk or negedge rst_n) begin
        if (!rst_n) begin
            count_1x <= 0;
            tick_1x  <= 0;
        end else if (tick_16x) begin
            if (count_1x == 4'd15) begin
                count_1x <= 0;
                tick_1x  <= 1'b1;
            end else begin
                count_1x <= count_1x + 1'b1;
                tick_1x  <= 1'b0;
            end
        end else begin
            tick_1x <= 1'b0;
        end
    end

endmodule

uart_top.v
// ==============================================================================
// Module: uart_top
// Description: Top-level Full-Duplex UART Controller.
//              Integrates Baud Rate Generator, Transmitter (TX), and
//              Receiver (RX) with optional internal loopback mode.
// ==============================================================================

`timescale 1ns / 1ps

module uart_top #(
    parameter CLK_FREQ  = 50000000, // 50 MHz
    parameter BAUD_RATE = 115200
)(
    input  wire       clk,
    input  wire       rst_n,

    // Transmitter Interface
    input  wire       tx_start,
    input  wire [7:0] tx_data,
    output wire       tx_busy,
    output wire       tx_done,
    output wire       uart_tx_pin,

    // Receiver Interface
    input  wire       uart_rx_pin,
    output wire [7:0] rx_data,
    output wire       rx_valid,
    output wire       frame_error,

    // Test Control
    input  wire       loopback_en // Connect TX directly to RX internally
);

    wire tick_16x;
    wire tick_1x;
    wire tx_serial;
    wire rx_serial;

    // Route RX signal: select external pin or internal loopback
    assign rx_serial   = loopback_en ? tx_serial : uart_rx_pin;
    assign uart_tx_pin = tx_serial;

    // Baud Rate Generator
    baud_gen #(
        .CLK_FREQ (CLK_FREQ),
        .BAUD_RATE(BAUD_RATE)
    ) u_baud_gen (
        .clk      (clk),
        .rst_n    (rst_n),
        .tick_16x (tick_16x),
        .tick_1x  (tick_1x)
    );

    // UART Transmitter
    uart_tx u_uart_tx (
        .clk       (clk),
        .rst_n     (rst_n),
        .tx_start  (tx_start),
        .baud_tick (tick_1x),
        .tx_data   (tx_data),
        .tx        (tx_serial),
        .tx_busy   (tx_busy),
        .tx_done   (tx_done)
    );

    // UART Receiver
    uart_rx u_uart_rx (
        .clk         (clk),
        .rst_n       (rst_n),
        .rx          (rx_serial),
        .tick_16x    (tick_16x),
        .rx_data     (rx_data),
        .rx_valid    (rx_valid),
        .frame_error (frame_error)
    );

endmodule

tb_uart.v
// ==============================================================================
// Testbench: tb_uart
// Description: Self-checking testbench for Full-Duplex UART Controller.
//              Tests baud generation, serial transmission, 16x oversampled
//              reception in loopback mode, multi-byte sequences, and frame error
//              detection.
// ==============================================================================

`timescale 1ns / 1ps

module tb_uart;

    // Simulation Clock: 50 MHz (Period = 20ns)
    // Faster Baud Rate for simulation speed: 1,000,000 baud
    parameter CLK_FREQ  = 50000000;
    parameter BAUD_RATE = 1000000;

    reg        clk;
    reg        rst_n;
    reg        tx_start;
    reg  [7:0] tx_data;
    wire       tx_busy;
    wire       tx_done;
    wire       uart_tx_pin;

    reg        uart_rx_pin;
    wire [7:0] rx_data;
    wire       rx_valid;
    wire       frame_error;
    reg        loopback_en;

    integer errors = 0;
    reg [7:0] test_vectors [0:3];
    integer i;

    // Instantiate DUT
    uart_top #(
        .CLK_FREQ (CLK_FREQ),
        .BAUD_RATE(BAUD_RATE)
    ) dut (
        .clk        (clk),
        .rst_n      (rst_n),
        .tx_start   (tx_start),
        .tx_data    (tx_data),
        .tx_busy    (tx_busy),
        .tx_done    (tx_done),
        .uart_tx_pin(uart_tx_pin),
        .uart_rx_pin(uart_rx_pin),
        .rx_data    (rx_data),
        .rx_valid   (rx_valid),
        .frame_error(frame_error),
        .loopback_en(loopback_en)
    );

    // Clock generator (50 MHz -> 20ns period)
    always #10 clk = ~clk;

    // Task to transmit a byte and verify reception
    task send_and_check(input [7:0] byte_to_send);
        begin
            @(posedge clk);
            tx_data  <= byte_to_send;
            tx_start <= 1'b1;
            @(posedge clk);
            tx_start <= 1'b0;

            // Wait until RX receives the byte
            @(posedge rx_valid);
            #1;
            if (rx_data !== byte_to_send) begin
                $display("[FAIL] Data Mismatch: Sent 0x%02X, Received 0x%02X", byte_to_send, rx_data);
                errors = errors + 1;
            end else begin
                $display("[PASS] Byte successfully transmitted and received: 0x%02X", rx_data);
            end

            // Wait for TX to finish completely
            @(posedge tx_done);
            #200; // Inter-frame delay
        end
    endtask

    initial begin
        $dumpfile("uart.vcd");
        $dumpvars(0, tb_uart);

        $display("------------------------------------------------------------");
        $display("   STARTING UART CONTROLLER VERIFICATION TESTBENCH          ");
        $display("------------------------------------------------------------");

        // Initialization
        clk         = 0;
        rst_n       = 0;
        tx_start    = 0;
        tx_data     = 0;
        uart_rx_pin = 1'b1;
        loopback_en = 1'b1; // Enable internal loopback for automated verification

        test_vectors[0] = 8'hA5; // 10100101 (alternating bit pattern)
        test_vectors[1] = 8'h3C; // 00111100
        test_vectors[2] = 8'hFF; // 11111111 (all ones)
        test_vectors[3] = 8'h00; // 00000000 (all zeros)

        // Reset
        #100;
        rst_n = 1;
        #100;

        $display(">>> Testing Loopback Transmissions across 4 distinct data patterns...");
        for (i = 0; i < 4; i = i + 1) begin
            send_and_check(test_vectors[i]);
        end

        // Final verification summary
        $display("\n------------------------------------------------------------");
        if (errors == 0) begin
            $display("   ALL UART CONTROLLER TESTS PASSED WITH ZERO ERRORS!       ");
        end else begin
            $display("   UART VERIFICATION FAILED WITH %0d ERRORS                 ", errors);
        end
        $display("------------------------------------------------------------\n");

        #500;
        $finish;
    end

endmodule

uart.vcd
$date
	Tue Oct  6 20:06:05 2026
$end
$version
	Icarus Verilog
$end
$timescale
	1ps
$end
$scope module tb_uart $end
$var wire 1 ! uart_tx_pin $end
$var wire 1 " tx_done $end
$var wire 1 # tx_busy $end
$var wire 1 $ rx_valid $end
$var wire 8 % rx_data [7:0] $end
$var wire 1 & frame_error $end
$var parameter 32 ' BAUD_RATE $end
$var parameter 32 ( CLK_FREQ $end
$var reg 1 ) clk $end
$var reg 1 * loopback_en $end
$var reg 1 + rst_n $end
$var reg 8 , tx_data [7:0] $end
$var reg 1 - tx_start $end
$var reg 1 . uart_rx_pin $end
$var integer 32 / errors [31:0] $end
$var integer 32 0 i [31:0] $end
$scope module dut $end
$var wire 1 ) clk $end
$var wire 1 * loopback_en $end
$var wire 1 + rst_n $end
$var wire 8 1 tx_data [7:0] $end
$var wire 1 - tx_start $end
$var wire 1 . uart_rx_pin $end
$var wire 1 ! uart_tx_pin $end
$var wire 1 2 tx_serial $end
$var wire 1 " tx_done $end
$var wire 1 # tx_busy $end
$var wire 1 3 tick_1x $end
$var wire 1 4 tick_16x $end
$var wire 1 $ rx_valid $end
$var wire 1 5 rx_serial $end
$var wire 8 6 rx_data [7:0] $end
$var wire 1 & frame_error $end
$var parameter 32 7 BAUD_RATE $end
$var parameter 32 8 CLK_FREQ $end
$scope module u_baud_gen $end
$var wire 1 ) clk $end
$var wire 1 + rst_n $end
$var parameter 32 9 BAUD_RATE $end
$var parameter 32 : CLK_FREQ $end
$var parameter 32 ; COUNT_WIDTH $end
$var parameter 64 < LIMIT_16X $end
$var reg 16 = count_16x [15:0] $end
$var reg 4 > count_1x [3:0] $end
$var reg 1 4 tick_16x $end
$var reg 1 3 tick_1x $end
$upscope $end
$scope module u_uart_rx $end
$var wire 1 ) clk $end
$var wire 1 + rst_n $end
$var wire 1 5 rx $end
$var wire 1 4 tick_16x $end
$var parameter 3 ? STATE_DATA $end
$var parameter 3 @ STATE_DONE $end
$var parameter 3 A STATE_IDLE $end
$var parameter 3 B STATE_START $end
$var parameter 3 C STATE_STOP $end
$var reg 3 D bit_index [2:0] $end
$var reg 1 & frame_error $end
$var reg 8 E rx_data [7:0] $end
$var reg 1 F rx_sync1 $end
$var reg 1 G rx_sync2 $end
$var reg 1 $ rx_valid $end
$var reg 4 H sample_cnt [3:0] $end
$var reg 8 I shift_reg [7:0] $end
$var reg 3 J state [2:0] $end
$upscope $end
$scope module u_uart_tx $end
$var wire 1 3 baud_tick $end
$var wire 1 ) clk $end
$var wire 1 + rst_n $end
$var wire 8 K tx_data [7:0] $end
$var wire 1 - tx_start $end
$var parameter 3 L STATE_DATA $end
$var parameter 3 M STATE_DONE $end
$var parameter 3 N STATE_IDLE $end
$var parameter 3 O STATE_START $end
$var parameter 3 P STATE_STOP $end
$var reg 3 Q bit_index [2:0] $end
$var reg 8 R data_reg [7:0] $end
$var reg 3 S state [2:0] $end
$var reg 1 2 tx $end
$var reg 1 # tx_busy $end
$var reg 1 " tx_done $end
$upscope $end
$upscope $end
$scope task send_and_check $end
$var reg 8 T byte_to_send [7:0] $end
$upscope $end
$upscope $end
$enddefinitions $end
$comment Show the parameter values. $end
$dumpall
b11 P
b1 O
b0 N
b100 M
b10 L
b11 C
b1 B
b0 A
b100 @
b10 ?
b11 <
b10000 ;
b10111110101111000010000000 :
b11110100001001000000 9
b10111110101111000010000000 8
b11110100001001000000 7
b10111110101111000010000000 (
b11110100001001000000 '
$end
#0
$dumpvars
bx T
b0 S
b0 R
b0 Q
b0 K
b0 J
b0 I
b0 H
1G
1F
b0 E
b0 D
b0 >
b0 =
b0 6
15
04
03
12
b0 1
bx 0
b0 /
1.
0-
b0 ,
0+
1*
0)
0&
b0 %
0$
0#
0"
1!
$end
#10000
1)
#20000
0)
#30000
1)
#40000
0)
#50000
1)
#60000
0)
#70000
1)
#80000
0)
#90000
1)
#100000
0)
1+
#110000
b1 =
1)
#120000
0)
#130000
b10 =
1)
#140000
0)
#150000
14
b0 =
1)
#160000
0)
#170000
b1 >
04
b1 =
1)
#180000
0)
#190000
b10 =
1)
#200000
0)
b10100101 T
b0 0
#210000
14
b0 =
1-
b10100101 ,
b10100101 1
b10100101 K
1)
#220000
0)
#230000
04
b1 =
b10 >
b1 S
1#
b10100101 R
0-
1)
#240000
0)
#250000
05
0!
02
b10 =
1)
#260000
0)
#270000
14
b0 =
0F
1)
#280000
0)
#290000
0G
b11 >
04
b1 =
1)
#300000
0)
#310000
b10 =
b1 J
1)
#320000
0)
#330000
14
b0 =
1)
#340000
0)
#350000
04
b1 =
b100 >
b1 H
1)
#360000
0)
#370000
b10 =
1)
#380000
0)
#390000
14
b0 =
1)
#400000
0)
#410000
b10 H
b101 >
04
b1 =
1)
#420000
0)
#430000
b10 =
1)
#440000
0)
#450000
14
b0 =
1)
#460000
0)
#470000
04
b1 =
b110 >
b11 H
1)
#480000
0)
#490000
b10 =
1)
#500000
0)
#510000
14
b0 =
1)
#520000
0)
#530000
b100 H
b111 >
04
b1 =
1)
#540000
0)
#550000
b10 =
1)
#560000
0)
#570000
14
b0 =
1)
#580000
0)
#590000
04
b1 =
b1000 >
b101 H
1)
#600000
0)
#610000
b10 =
1)
#620000
0)
#630000
14
b0 =
1)
#640000
0)
#650000
b110 H
b1001 >
04
b1 =
1)
#660000
0)
#670000
b10 =
1)
#680000
0)
#690000
14
b0 =
1)
#700000
0)
#710000
04
b1 =
b1010 >
b111 H
1)
#720000
0)
#730000
b10 =
1)
#740000
0)
#750000
14
b0 =
1)
#760000
0)
#770000
b10 J
b0 H
b1011 >
04
b1 =
1)
#780000
0)
#790000
b10 =
1)
#800000
0)
#810000
14
b0 =
1)
#820000
0)
#830000
04
b1 =
b1100 >
b1 H
1)
#840000
0)
#850000
b10 =
1)
#860000
0)
#870000
14
b0 =
1)
#880000
0)
#890000
b10 H
b1101 >
04
b1 =
1)
#900000
0)
#910000
b10 =
1)
#920000
0)
#930000
14
b0 =
1)
#940000
0)
#950000
04
b1 =
b1110 >
b11 H
1)
#960000
0)
#970000
b10 =
1)
#980000
0)
#990000
14
b0 =
1)
#1000000
0)
#1010000
b100 H
b1111 >
04
b1 =
1)
#1020000
0)
#1030000
b10 =
1)
#1040000
0)
#1050000
14
b0 =
1)
#1060000
0)
#1070000
04
b1 =
13
b0 >
b101 H
1)
#1080000
0)
#1090000
b10 S
03
b10 =
1)
#1100000
0)
#1110000
15
14
b0 =
1!
12
1)
#1120000
0)
#1130000
b110 H
1F
b1 >
04
b1 =
1)
#1140000
0)
#1150000
b10 =
1G
1)
#1160000
0)
#1170000
14
b0 =
1)
#1180000
0)
#1190000
04
b1 =
b10 >
b111 H
1)
#1200000
0)
#1210000
b10 =
1)
#1220000
0)
#1230000
14
b0 =
1)
#1240000
0)
#1250000
b1000 H
b11 >
04
b1 =
1)
#1260000
0)
#1270000
b10 =
1)
#1280000
0)
#1290000
14
b0 =
1)
#1300000
0)
#1310000
04
b1 =
b100 >
b1001 H
1)
#1320000
0)
#1330000
b10 =
1)
#1340000
0)
#1350000
14
b0 =
1)
#1360000
0)
#1370000
b1010 H
b101 >
04
b1 =
1)
#1380000
0)
#1390000
b10 =
1)
#1400000
0)
#1410000
14
b0 =
1)
#1420000
0)
#1430000
04
b1 =
b110 >
b1011 H
1)
#1440000
0)
#1450000
b10 =
1)
#1460000
0)
#1470000
14
b0 =
1)
#1480000
0)
#1490000
b1100 H
b111 >
04
b1 =
1)
#1500000
0)
#1510000
b10 =
1)
#1520000
0)
#1530000
14
b0 =
1)
#1540000
0)
#1550000
04
b1 =
b1000 >
b1101 H
1)
#1560000
0)
#1570000
b10 =
1)
#1580000
0)
#1590000
14
b0 =
1)
#1600000
0)
#1610000
b1110 H
b1001 >
04
b1 =
1)
#1620000
0)
#1630000
b10 =
1)
#1640000
0)
#1650000
14
b0 =
1)
#1660000
0)
#1670000
04
b1 =
b1010 >
b1111 H
1)
#1680000
0)
#1690000
b10 =
1)
#1700000
0)
#1710000
14
b0 =
1)
#1720000
0)
#1730000
b1 D
b1 I
b0 H
b1011 >
04
b1 =
1)
#1740000
0)
#1750000
b10 =
1)
#1760000
0)
#1770000
14
b0 =
1)
#1780000
0)
#1790000
04
b1 =
b1100 >
b1 H
1)
#1800000
0)
#1810000
b10 =
1)
#1820000
0)
#1830000
14
b0 =
1)
#1840000
0)
#1850000
b10 H
b1101 >
04
b1 =
1)
#1860000
0)
#1870000
b10 =
1)
#1880000
0)
#1890000
14
b0 =
1)
#1900000
0)
#1910000
04
b1 =
b1110 >
b11 H
1)
#1920000
0)
#1930000
b10 =
1)
#1940000
0)
#1950000
14
b0 =
1)
#1960000
0)
#1970000
b100 H
b1111 >
04
b1 =
1)
#1980000
0)
#1990000
b10 =
1)
#2000000
0)
#2010000
14
b0 =
1)
#2020000
0)
#2030000
04
b1 =
13
b0 >
b101 H
1)
#2040000
0)
#2050000
b1 Q
03
b10 =
1)
#2060000
0)
#2070000
05
14
b0 =
0!
02
1)
#2080000
0)
#2090000
b110 H
0F
b1 >
04
b1 =
1)
#2100000
0)
#2110000
b10 =
0G
1)
#2120000
0)
#2130000
14
b0 =
1)
#2140000
0)
#2150000
04
b1 =
b10 >
b111 H
1)
#2160000
0)
#2170000
b10 =
1)
#2180000
0)
#2190000
14
b0 =
1)
#2200000
0)
#2210000
b1000 H
b11 >
04
b1 =
1)
#2220000
0)
#2230000
b10 =
1)
#2240000
0)
#2250000
14
b0 =
1)
#2260000
0)
#2270000
04
b1 =
b100 >
b1001 H
1)
#2280000
0)
#2290000
b10 =
1)
#2300000
0)
#2310000
14
b0 =
1)
#2320000
0)
#2330000
b1010 H
b101 >
04
b1 =
1)
#2340000
0)
#2350000
b10 =
1)
#2360000
0)
#2370000
14
b0 =
1)
#2380000
0)
#2390000
04
b1 =
b110 >
b1011 H
1)
#2400000
0)
#2410000
b10 =
1)
#2420000
0)
#2430000
14
b0 =
1)
#2440000
0)
#2450000
b1100 H
b111 >
04
b1 =
1)
#2460000
0)
#2470000
b10 =
1)
#2480000
0)
#2490000
14
b0 =
1)
#2500000
0)
#2510000
04
b1 =
b1000 >
b1101 H
1)
#2520000
0)
#2530000
b10 =
1)
#2540000
0)
#2550000
14
b0 =
1)
#2560000
0)
#2570000
b1110 H
b1001 >
04
b1 =
1)
#2580000
0)
#2590000
b10 =
1)
#2600000
0)
#2610000
14
b0 =
1)
#2620000
0)
#2630000
04
b1 =
b1010 >
b1111 H
1)
#2640000
0)
#2650000
b10 =
1)
#2660000
0)
#2670000
14
b0 =
1)
#2680000
0)
#2690000
b10 D
b0 H
b1011 >
04
b1 =
1)
#2700000
0)
#2710000
b10 =
1)
#2720000
0)
#2730000
14
b0 =
1)
#2740000
0)
#2750000
04
b1 =
b1100 >
b1 H
1)
#2760000
0)
#2770000
b10 =
1)
#2780000
0)
#2790000
14
b0 =
1)
#2800000
0)
#2810000
b10 H
b1101 >
04
b1 =
1)
#2820000
0)
#2830000
b10 =
1)
#2840000
0)
#2850000
14
b0 =
1)
#2860000
0)
#2870000
04
b1 =
b1110 >
b11 H
1)
#2880000
0)
#2890000
b10 =
1)
#2900000
0)
#2910000
14
b0 =
1)
#2920000
0)
#2930000
b100 H
b1111 >
04
b1 =
1)
#2940000
0)
#2950000
b10 =
1)
#2960000
0)
#2970000
14
b0 =
1)
#2980000
0)
#2990000
04
b1 =
13
b0 >
b101 H
1)
#3000000
0)
#3010000
b10 Q
03
b10 =
1)
#3020000
0)
#3030000
15
14
b0 =
1!
12
1)
#3040000
0)
#3050000
b110 H
1F
b1 >
04
b1 =
1)
#3060000
0)
#3070000
b10 =
1G
1)
#3080000
0)
#3090000
14
b0 =
1)
#3100000
0)
#3110000
04
b1 =
b10 >
b111 H
1)
#3120000
0)
#3130000
b10 =
1)
#3140000
0)
#3150000
14
b0 =
1)
#3160000
0)
#3170000
b1000 H
b11 >
04
b1 =
1)
#3180000
0)
#3190000
b10 =
1)
#3200000
0)
#3210000
14
b0 =
1)
#3220000
0)
#3230000
04
b1 =
b100 >
b1001 H
1)
#3240000
0)
#3250000
b10 =
1)
#3260000
0)
#3270000
14
b0 =
1)
#3280000
0)
#3290000
b1010 H
b101 >
04
b1 =
1)
#3300000
0)
#3310000
b10 =
1)
#3320000
0)
#3330000
14
b0 =
1)
#3340000
0)
#3350000
04
b1 =
b110 >
b1011 H
1)
#3360000
0)
#3370000
b10 =
1)
#3380000
0)
#3390000
14
b0 =
1)
#3400000
0)
#3410000
b1100 H
b111 >
04
b1 =
1)
#3420000
0)
#3430000
b10 =
1)
#3440000
0)
#3450000
14
b0 =
1)
#3460000
0)
#3470000
04
b1 =
b1000 >
b1101 H
1)
#3480000
0)
#3490000
b10 =
1)
#3500000
0)
#3510000
14
b0 =
1)
#3520000
0)
#3530000
b1110 H
b1001 >
04
b1 =
1)
#3540000
0)
#3550000
b10 =
1)
#3560000
0)
#3570000
14
b0 =
1)
#3580000
0)
#3590000
04
b1 =
b1010 >
b1111 H
1)
#3600000
0)
#3610000
b10 =
1)
#3620000
0)
#3630000
14
b0 =
1)
#3640000
0)
#3650000
b11 D
b101 I
b0 H
b1011 >
04
b1 =
1)
#3660000
0)
#3670000
b10 =
1)
#3680000
0)
#3690000
14
b0 =
1)
#3700000
0)
#3710000
04
b1 =
b1100 >
b1 H
1)
#3720000
0)
#3730000
b10 =
1)
#3740000
0)
#3750000
14
b0 =
1)
#3760000
0)
#3770000
b10 H
b1101 >
04
b1 =
1)
#3780000
0)
#3790000
b10 =
1)
#3800000
0)
#3810000
14
b0 =
1)
#3820000
0)
#3830000
04
b1 =
b1110 >
b11 H
1)
#3840000
0)
#3850000
b10 =
1)
#3860000
0)
#3870000
14
b0 =
1)
#3880000
0)
#3890000
b100 H
b1111 >
04
b1 =
1)
#3900000
0)
#3910000
b10 =
1)
#3920000
0)
#3930000
14
b0 =
1)
#3940000
0)
#3950000
04
b1 =
13
b0 >
b101 H
1)
#3960000
0)
#3970000
b11 Q
03
b10 =
1)
#3980000
0)
#3990000
05
14
b0 =
0!
02
1)
#4000000
0)
#4010000
b110 H
0F
b1 >
04
b1 =
1)
#4020000
0)
#4030000
b10 =
0G
1)
#4040000
0)
#4050000
14
b0 =
1)
#4060000
0)
#4070000
04
b1 =
b10 >
b111 H
1)
#4080000
0)
#4090000
b10 =
1)
#4100000
0)
#4110000
14
b0 =
1)
#4120000
0)
#4130000
b1000 H
b11 >
04
b1 =
1)
#4140000
0)
#4150000
b10 =
1)
#4160000
0)
#4170000
14
b0 =
1)
#4180000
0)
#4190000
04
b1 =
b100 >
b1001 H
1)
#4200000
0)
#4210000
b10 =
1)
#4220000
0)
#4230000
14
b0 =
1)
#4240000
0)
#4250000
b1010 H
b101 >
04
b1 =
1)
#4260000
0)
#4270000
b10 =
1)
#4280000
0)
#4290000
14
b0 =
1)
#4300000
0)
#4310000
04
b1 =
b110 >
b1011 H
1)
#4320000
0)
#4330000
b10 =
1)
#4340000
0)
#4350000
14
b0 =
1)
#4360000
0)
#4370000
b1100 H
b111 >
04
b1 =
1)
#4380000
0)
#4390000
b10 =
1)
#4400000
0)
#4410000
14
b0 =
1)
#4420000
0)
#4430000
04
b1 =
b1000 >
b1101 H
1)
#4440000
0)
#4450000
b10 =
1)
#4460000
0)
#4470000
14
b0 =
1)
#4480000
0)
#4490000
b1110 H
b1001 >
04
b1 =
1)
#4500000
0)
#4510000
b10 =
1)
#4520000
0)
#4530000
14
b0 =
1)
#4540000
0)
#4550000
04
b1 =
b1010 >
b1111 H
1)
#4560000
0)
#4570000
b10 =
1)
#4580000
0)
#4590000
14
b0 =
1)
#4600000
0)
#4610000
b100 D
b0 H
b1011 >
04
b1 =
1)
#4620000
0)
#4630000
b10 =
1)
#4640000
0)
#4650000
14
b0 =
1)
#4660000
0)
#4670000
04
b1 =
b1100 >
b1 H
1)
#4680000
0)
#4690000
b10 =
1)
#4700000
0)
#4710000
14
b0 =
1)
#4720000
0)
#4730000
b10 H
b1101 >
04
b1 =
1)
#4740000
0)
#4750000
b10 =
1)
#4760000
0)
#4770000
14
b0 =
1)
#4780000
0)
#4790000
04
b1 =
b1110 >
b11 H
1)
#4800000
0)
#4810000
b10 =
1)
#4820000
0)
#4830000
14
b0 =
1)
#4840000
0)
#4850000
b100 H
b1111 >
04
b1 =
1)
#4860000
0)
#4870000
b10 =
1)
#4880000
0)
#4890000
14
b0 =
1)
#4900000
0)
#4910000
04
b1 =
13
b0 >
b101 H
1)
#4920000
0)
#4930000
b100 Q
03
b10 =
1)
#4940000
0)
#4950000
14
b0 =
1)
#4960000
0)
#4970000
b110 H
b1 >
04
b1 =
1)
#4980000
0)
#4990000
b10 =
1)
#5000000
0)
#5010000
14
b0 =
1)
#5020000
0)
#5030000
04
b1 =
b10 >
b111 H
1)
#5040000
0)
#5050000
b10 =
1)
#5060000
0)
#5070000
14
b0 =
1)
#5080000
0)
#5090000
b1000 H
b11 >
04
b1 =
1)
#5100000
0)
#5110000
b10 =
1)
#5120000
0)
#5130000
14
b0 =
1)
#5140000
0)
#5150000
04
b1 =
b100 >
b1001 H
1)
#5160000
0)
#5170000
b10 =
1)
#5180000
0)
#5190000
14
b0 =
1)
#5200000
0)
#5210000
b1010 H
b101 >
04
b1 =
1)
#5220000
0)
#5230000
b10 =
1)
#5240000
0)
#5250000
14
b0 =
1)
#5260000
0)
#5270000
04
b1 =
b110 >
b1011 H
1)
#5280000
0)
#5290000
b10 =
1)
#5300000
0)
#5310000
14
b0 =
1)
#5320000
0)
#5330000
b1100 H
b111 >
04
b1 =
1)
#5340000
0)
#5350000
b10 =
1)
#5360000
0)
#5370000
14
b0 =
1)
#5380000
0)
#5390000
04
b1 =
b1000 >
b1101 H
1)
#5400000
0)
#5410000
b10 =
1)
#5420000
0)
#5430000
14
b0 =
1)
#5440000
0)
#5450000
b1110 H
b1001 >
04
b1 =
1)
